yaml_dataclass/__init__.py
yaml_dataclass/printing.py
yaml_dataclass/settings.py
yaml_dataclass-0.1.3.dist-info/METADATA
yaml_dataclass-0.1.3.dist-info/WHEEL
yaml_dataclass-0.1.3.dist-info/RECORD
