Metadata-Version: 2.1
Name: yaml-dataclass
Version: 0.1.3
Summary: Simple Settings Base Class for Handling YAML settings
License: MIT
Author: Gereon Tombrink
Author-email: tombrink@igg.uni-bonn.de
Requires-Python: >=3.8.2,<3.12
Classifier: License :: OSI Approved :: MIT License
Classifier: Programming Language :: Python :: 3
Classifier: Programming Language :: Python :: 3.9
Classifier: Programming Language :: Python :: 3.10
Classifier: Programming Language :: Python :: 3.11
Requires-Dist: PyYAML (>=6.0.1)
Requires-Dist: colorama (>=0.4.6,<0.5.0)
Requires-Dist: pydantic (>=2.4.2,<3.0.0)
